ltfmselector/__init__.py
ltfmselector/env.py
ltfmselector/ltfmselector.py
ltfmselector/py.typed
ltfmselector/utils.py
ltfmselector-0.2.0.dist-info/METADATA
ltfmselector-0.2.0.dist-info/WHEEL
ltfmselector-0.2.0.dist-info/licenses/LICENSE
ltfmselector-0.2.0.dist-info/RECORD
