Metadata-Version: 2.4
Name: ltfmselector
Version: 0.2.0
Summary: Locally-Tailored Feature and Model Selector with Deep Q-Learning
Project-URL: GitHub, https://github.com/RenZhen95/ltfmselector/
Author-email: RenZhen95 <j-liaw@hotmail.com>
License: MIT License
License-File: LICENSE
Requires-Python: >=3.12
Requires-Dist: gymnasium>=1.1.1
Requires-Dist: matplotlib>=3.10.1
Requires-Dist: numpy>=2.2.4
Requires-Dist: openpyxl>=3.1.5
Requires-Dist: pandas>=2.2.3
Requires-Dist: scikit-learn<1.6
Requires-Dist: seaborn>=0.13.2
Requires-Dist: tensorboard>=2.20.0
Requires-Dist: torch>=2.6.0
